adax/__init__.py
adax-0.4.0.dist-info/LICENSE
adax-0.4.0.dist-info/METADATA
adax-0.4.0.dist-info/WHEEL
adax-0.4.0.dist-info/top_level.txt
adax-0.4.0.dist-info/RECORD
